asimov/__init__.py
asimov/asimov_base.py
asimov/constants.py
asimov/py.typed
asimov/caches/cache.py
asimov/caches/mock_redis_cache.py
asimov/caches/redis_cache.py
asimov/data/postgres/manager.py
asimov/executors/__init__.py
asimov/executors/executor.py
asimov/graph/__init__.py
asimov/graph/agent_directed_flow.py
asimov/graph/tasks.py
asimov/services/inference_clients.py
asimov/utils/models.py
asimov/utils/token_buffer.py
asimov/utils/visualize.py
asimov_agents-0.6.0.dist-info/METADATA
asimov_agents-0.6.0.dist-info/WHEEL
asimov_agents-0.6.0.dist-info/licenses/LICENSE
asimov_agents-0.6.0.dist-info/RECORD
