Metadata-Version: 2.4
Name: asimov-agents
Version: 0.6.0
Summary: A library of primitives for building agentic flows.
Project-URL: Homepage, https://github.com/BismuthCloud/asimov
Project-URL: URL, https://github.com/BismuthCloud/asimov
Project-URL: Documentation, https://github.com/BismuthCloud/asimov
Project-URL: Issues, https://github.com/BismuthCloud/asimov/issues
Project-URL: Source, https://github.com/BismuthCloud/asimov
Author-email: Ian Butler <ian@bismuth.cloud>
License-Expression: Apache-2.0
License-File: LICENSE
Keywords: agent,ai,bismuth,git
Classifier: Development Status :: 4 - Beta
Classifier: Programming Language :: Python
Classifier: Programming Language :: Python :: 3.12
Classifier: Programming Language :: Python :: Implementation :: CPython
Classifier: Programming Language :: Python :: Implementation :: PyPy
Requires-Python: >=3.12
Requires-Dist: aioboto3>=13.0.0
Requires-Dist: backoff>=2.2.0
Requires-Dist: gitpython<4.0.0,>=3.1.0
Requires-Dist: google-cloud-aiplatform==1.69.0
Requires-Dist: google-genai
Requires-Dist: google-generativeai==0.8.3
Requires-Dist: httpx<1.0.0,>=0.23.0
Requires-Dist: jsonpickle>=3.0.0
Requires-Dist: lupa==2.2.0
Requires-Dist: opentelemetry-api>=1.27.0
Requires-Dist: opentelemetry-instrumentation-httpx
Requires-Dist: opentelemetry-instrumentation-psycopg2
Requires-Dist: psycopg2-binary>=2.9.0
Requires-Dist: pydantic>=2.0.0
Requires-Dist: redis>=5.0.0
Provides-Extra: dev
Requires-Dist: black>=23.1.0; extra == 'dev'
Requires-Dist: graphviz; extra == 'dev'
Requires-Dist: mypy>=1.0.0; extra == 'dev'
Requires-Dist: pytest-asyncio>=0.24.0; extra == 'dev'
Requires-Dist: pytest-cov>=4.0.0; extra == 'dev'
Requires-Dist: pytest>=7.0.0; extra == 'dev'
